wled/__init__.py
wled/cli/__init__.py
wled/cli/async_typer.py
wled/exceptions.py
wled/models.py
wled/py.typed
wled/wled.py
py_wled-0.1.1.dist-info/METADATA
py_wled-0.1.1.dist-info/WHEEL
py_wled-0.1.1.dist-info/entry_points.txt
py_wled-0.1.1.dist-info/RECORD
