Metadata-Version: 2.1
Name: py-wled
Version: 0.1.1
Summary: Asynchronous Python client for WLED.
Home-page: https://github.com/frenck/python-wled
License: MIT
Keywords: wled,api,async,client
Author: Franck Nijhof
Author-email: opensource@frenck.dev
Maintainer: Franck Nijhof
Maintainer-email: opensource@frenck.dev
Requires-Python: >=3.11,<4.0
Classifier: Development Status :: 4 - Beta
Classifier: Framework :: AsyncIO
Classifier: Intended Audience :: Developers
Classifier: License :: OSI Approved :: MIT License
Classifier: Natural Language :: English
Classifier: Programming Language :: Python :: 3
Classifier: Programming Language :: Python :: 3.11
Classifier: Programming Language :: Python :: 3.12
Classifier: Topic :: Software Development :: Libraries :: Python Modules
Provides-Extra: cli
Requires-Dist: aiohttp (>=3.0.0)
Requires-Dist: awesomeversion (>=22.1.0)
Requires-Dist: backoff (>=2.2.0)
Requires-Dist: cachetools (>=4.0.0)
Requires-Dist: typer[all] (>=0.12.3,<0.13.0) ; extra == "cli"
Requires-Dist: yarl (>=1.6.0)
Requires-Dist: zeroconf[all] (>=0.132.2,<0.133.0) ; extra == "cli"
Project-URL: Bug Tracker, https://github.com/frenck/python-wled/issues
Project-URL: Changelog, https://github.com/frenck/python-wled/releases
Project-URL: Documentation, https://github.com/frenck/python-wled
Project-URL: Repository, https://github.com/frenck/python-wled
